{"child_modules": [], "dep_prios": [5, 5], "version_id": "0.511", "mtime": 1497053249.0, "data_mtime": 1497054954.0, "dependencies": ["abc", "builtins"], "suppressed": [], "size": 911, "id": "ICommandFactory", "options": {"warn_return_any": true, "follow_imports": "silent", "quick_and_dirty": false, "strict_boolean": false, "show_none_errors": true, "disallow_untyped_calls": true, "debug_cache": false, "strict_optional": true, "check_untyped_defs": true, "ignore_errors": false, "disallow_untyped_defs": true, "strict_optional_whitelist": null, "warn_no_return": true, "ignore_missing_imports": false}, "path": "/Users/kkbnart/Documents/programming/ProgramaticProgrammer/ex5/ICommandFactory.py", "interface_hash": "5d824a76298e79e4840148c29cfcd631"}